bert_server_client/__init__.py
bert_server_client/client.py
bert_server_client/error.py
bert_server_client/schema/__init__.py
bert_server_client/schema/base.py
bert_server_client/schema/document.py
bert_server_client/schema/embedding.py
bert_server_client/schema/health_check.py
bert_server_client/schema/split.py
bert_server_client/schema/zmq_message_header.py
bert_server_client/tests/__init__.py
bert_server_client/tests/client_integration_tests.py
bert_server_client/tests/test_base.py
bert_server_client/tests/test_client.py
bert_server_client/tests/test_msgpack.py
bert_server_client/tests/test_zmq_message_header.py
bert_server_client-1.2.4.dist-info/METADATA
bert_server_client-1.2.4.dist-info/WHEEL
bert_server_client-1.2.4.dist-info/top_level.txt
bert_server_client-1.2.4.dist-info/RECORD
